{
  "version": "7",
  "dialect": "postgresql",
  "entries": [
    {
      "idx": 0,
      "version": "7",
      "when": 1760462064504,
      "tag": "0000_new_strong_guy",
      "breakpoints": true
    },
    {
      "idx": 1,
      "version": "7",
      "when": 1760512543913,
      "tag": "0001_tidy_jocasta",
      "breakpoints": true
    },
    {
      "idx": 2,
      "version": "7",
      "when": 1760513341062,
      "tag": "0002_sturdy_fenris",
      "breakpoints": true
    },
    {
      "idx": 3,
      "version": "7",
      "when": 1762110529836,
      "tag": "0003_tan_mac_gargan",
      "breakpoints": true
    },
    {
      "idx": 4,
      "version": "7",
      "when": 1763142315596,
      "tag": "0004_awesome_gateway",
      "breakpoints": true
    },
    {
      "idx": 5,
      "version": "7",
      "when": 1763188662930,
      "tag": "0005_cute_jasper_sitwell",
      "breakpoints": true
    }
  ]
}